{
  "card_type": "stat_card",
  "name": "EZEKIEL",
  "title": null,
  "faction": "Resurrectionists",
  "station": null,
  "model_limit": 1,
  "cost": "7",
  "df": 5,
  "wp": 5,
  "sz": 1,
  "sp": 6,
  "health": 9,
  "soulstone_cache": null,
  "shields": 0,
  "base_size": "30mm",
  "infuses_soulstone_on_death": false,
  "crew_card_name": null,
  "totem": null,
  "characteristics": [
    "Unique",
    "Living",
    "Versatile"
  ],
  "keywords": [],
  "abilities": [
    {
      "name": "Protected (Undead)",
      "defensive_type": "unusual_defense",
      "text": "After an enemy model targets this model, this model may discard a card. If it does so, a friendly undead model within 2\" suffers any effects generated by that action."
    },
    {
      "name": "Resilient",
      "defensive_type": "fortitude",
      "text": "Attacks targeting this model reduce raises they receive by 1 (to a minimum of 0)."
    },
    {
      "name": "Trample",
      "defensive_type": null,
      "text": "This model can move through other models."
    }
  ],
  "actions": [
    {
      "name": "Fresh Meat",
      "action_type": "magic",
      "range": "(magic)10\"",
      "skill_value": 6,
      "skill_built_in_suit": null,
      "skill_fate_modifier": null,
      "resist": "Wp",
      "tn": null,
      "damage": "1",
      "is_signature": false,
      "soulstone_cost": 0,
      "costs_and_restrictions": "A friendly undead model in LoS of the target may move up to 5\" toward the target.",
      "effects": null,
      "triggers": [
        {
          "name": "Clawed to Pieces",
          "suit": "(r)",
          "timing": "when_resolving",
          "text": "When resolving, if the target is within 1\" of a Mindless Zombie, this action deals +1 damage to it.",
          "is_mandatory": false,
          "soulstone_cost": 0
        },
        {
          "name": "Resurrect",
          "suit": "(c)",
          "timing": "after_succeeding",
          "text": "Enemy only. Summon a Mindless Zombie in base contact with the target.",
          "is_mandatory": false,
          "soulstone_cost": 0
        }
      ],
      "category": "attack_actions"
    },
    {
      "name": "Return of the Living Dead",
      "range": "6\"",
      "skill_value": 0,
      "skill_built_in_suit": null,
      "skill_fate_modifier": null,
      "tn": 4,
      "damage": null,
      "is_signature": false,
      "soulstone_cost": 0,
      "costs_and_restrictions": "This action has a raise value of 3.",
      "effects": "Summon one Mindless Zombie within range. For each raise this action receives, summon an additional Mindless Zombie within range.",
      "triggers": [],
      "category": "tactical_actions",
      "action_type": null
    },
    {
      "name": "Healing Energy",
      "range": "8\"",
      "skill_value": 0,
      "skill_built_in_suit": null,
      "skill_fate_modifier": null,
      "tn": 4,
      "damage": null,
      "is_signature": false,
      "soulstone_cost": 0,
      "costs_and_restrictions": null,
      "effects": "Target heals 2. For each raise this action receives, the target heals an additional +2.",
      "triggers": [
        {
          "name": "Necromatic Rituals",
          "suit": "(c)",
          "timing": "when_resolving",
          "text": "Kill a friendly Mindless Zombie within 2\" of the target. When resolving, the target heals +2.",
          "is_mandatory": false,
          "soulstone_cost": 0
        }
      ],
      "category": "tactical_actions",
      "action_type": null
    },
    {
      "name": "Intuition",
      "range": null,
      "skill_value": null,
      "skill_built_in_suit": null,
      "skill_fate_modifier": null,
      "tn": null,
      "damage": null,
      "is_signature": true,
      "soulstone_cost": 0,
      "costs_and_restrictions": "Once per turn.",
      "effects": "Look at the top three cards of your fate deck and then return them in any order.",
      "triggers": [],
      "category": "tactical_actions",
      "action_type": null
    }
  ],
  "source_pdf": "C:\\Users\\mbeck\\Documents\\GitHub\\Malifaux-4th-Edition-Tools\\source_pdfs\\Resurrectionists\\Versatile - Resurrectionists\\M4E_Stat_Res-Versatile_Ezekiel.pdf",
  "merge_warnings": [],
  "extraction_notes": [],
  "factions": [
    "Resurrectionists"
  ]
}