{
  "card_type": "stat_card",
  "name": "Carrion Fate",
  "title": "Emissary",
  "faction": "Outcasts",
  "station": null,
  "model_limit": 1,
  "cost": "8",
  "df": 5,
  "wp": 6,
  "sz": 3,
  "sp": 6,
  "health": 11,
  "soulstone_cache": null,
  "shields": 0,
  "base_size": "50mm",
  "infuses_soulstone_on_death": false,
  "crew_card_name": null,
  "totem": null,
  "characteristics": [
    "Unique",
    "Living",
    "Versatile"
  ],
  "keywords": [],
  "abilities": [
    {
      "name": "Quick Study",
      "defensive_type": null,
      "text": "This model gains the keywords of the friendly leader."
    },
    {
      "name": "Tempting Fate",
      "defensive_type": null,
      "text": "Once per game. When a friendly master is killed, this model may drain two (soulstone). If it does so, deal 4 irreducible damage to this model, then the friendly master heals 4."
    },
    {
      "name": "Terrifying Presence",
      "defensive_type": "unusual_defense",
      "text": "Enemy attack actions that target friendly models within 2\" suffer a (-) to their duels."
    }
  ],
  "actions": [
    {
      "name": "Carrion Crow",
      "action_type": "melee",
      "range": "(melee)2\"",
      "skill_value": 7,
      "skill_built_in_suit": null,
      "skill_fate_modifier": null,
      "resist": "Df",
      "tn": null,
      "damage": "2",
      "is_signature": false,
      "soulstone_cost": 0,
      "costs_and_restrictions": null,
      "effects": "This action deals +1 damage for each Remains marker within 2\" of the target. Then, remove a Remains marker within 2\" of the target.",
      "triggers": [
        {
          "name": "Heave",
          "suit": "(r)",
          "timing": "after_succeeding",
          "text": "Place the target anywhere within 3\" of this model.",
          "is_mandatory": false,
          "soulstone_cost": 0
        },
        {
          "name": "Infect",
          "suit": "(c)",
          "timing": "after_succeeding",
          "text": "Target gains a Poison token.",
          "is_mandatory": false,
          "soulstone_cost": 0
        }
      ],
      "category": "attack_actions"
    },
    {
      "name": "Fly With Me",
      "range": "4\"",
      "skill_value": 0,
      "skill_built_in_suit": null,
      "skill_fate_modifier": null,
      "tn": 5,
      "damage": null,
      "is_signature": true,
      "soulstone_cost": 0,
      "costs_and_restrictions": "This model may target a friendly model within 2\".",
      "effects": "Place this model within range. If this action received a raise, place the target (if any) in base contact with this model.",
      "triggers": [
        {
          "name": "Puncturing Talons",
          "suit": "(r)",
          "timing": "when_resolving",
          "text": "When resolving, this action receives one additional raise.",
          "is_mandatory": false,
          "soulstone_cost": 0
        }
      ],
      "category": "tactical_actions",
      "action_type": null
    }
  ],
  "source_pdf": "C:\\Users\\mbeck\\Documents\\GitHub\\Malifaux-4th-Edition-Tools\\source_pdfs\\Resurrectionists\\Versatile - Resurrectionists\\M4E_Stat_Res-Versatile_Carrion_Fate_Emissary.pdf",
  "merge_warnings": [],
  "extraction_notes": [],
  "factions": [
    "Outcasts",
    "Resurrectionists"
  ]
}