{
  "card_type": "stat_card",
  "name": "Young Nephilim",
  "title": null,
  "faction": "Neverborn",
  "station": "Minion",
  "model_limit": 4,
  "cost": "6",
  "df": 5,
  "wp": 5,
  "sz": 2,
  "sp": 6,
  "health": 8,
  "soulstone_cache": null,
  "shields": 0,
  "base_size": "40mm",
  "infuses_soulstone_on_death": false,
  "crew_card_name": null,
  "totem": null,
  "characteristics": [
    "Minion (4)",
    "Living",
    "Brood"
  ],
  "keywords": [],
  "abilities": [
    {
      "name": "Flight",
      "defensive_type": null,
      "text": "This model ignores terrain and other models while moving."
    },
    {
      "name": "Relish in Blood (Mature Nephilim)",
      "defensive_type": null,
      "text": "After resolving an attack action that damaged a model, this model may remove a Glutted token to replace itself with a Mature Nephilim and heal 4. If it does not have a Glutted token, it instead gains a Glutted token."
    }
  ],
  "actions": [
    {
      "name": "Deadly Claws",
      "action_type": "melee",
      "range": "(melee)1\"",
      "skill_value": 5,
      "skill_built_in_suit": "t",
      "skill_fate_modifier": null,
      "resist": "Df",
      "tn": null,
      "damage": "2",
      "is_signature": false,
      "soulstone_cost": 0,
      "costs_and_restrictions": null,
      "effects": "If this action was generated by the Charge action, it deals +1 damage.",
      "triggers": [
        {
          "name": "Pick the Bones",
          "suit": "(c)",
          "timing": "after_succeeding",
          "text": "After killing, this model may declare the Interact action after resolving the current action.",
          "is_mandatory": false,
          "soulstone_cost": 0
        }
      ],
      "category": "attack_actions"
    },
    {
      "name": "Blacken the Skies",
      "range": "5\"",
      "skill_value": 0,
      "skill_built_in_suit": null,
      "skill_fate_modifier": null,
      "tn": 6,
      "damage": null,
      "is_signature": true,
      "soulstone_cost": 0,
      "costs_and_restrictions": "All friendly models within (t)2\" with this action that have already activated this turn may declare this action.",
      "effects": "Place this model within range. This model may not declare the Interact action this activation.",
      "triggers": [
        {
          "name": "Inspiration",
          "suit": "(c)",
          "timing": "after_succeeding",
          "text": "This model gains a Focused token.",
          "is_mandatory": false,
          "soulstone_cost": 0
        }
      ],
      "category": "tactical_actions",
      "action_type": null
    }
  ],
  "source_pdf": "C:\\Users\\mbeck\\Documents\\GitHub\\Malifaux-4th-Edition-Tools\\source_pdfs\\Neverborn\\Brood\\M4E_Stat_Brood_Young_Nephilim_A.pdf",
  "merge_warnings": [],
  "extraction_notes": [],
  "factions": [
    "Neverborn"
  ]
}