{
  "card_type": "stat_card",
  "name": "Nia",
  "title": "Fractured Future",
  "faction": "Ten Thunders",
  "station": null,
  "model_limit": 1,
  "cost": "7",
  "df": 5,
  "wp": 5,
  "sz": 2,
  "sp": 6,
  "health": 9,
  "soulstone_cache": null,
  "shields": 0,
  "base_size": "30mm",
  "infuses_soulstone_on_death": false,
  "crew_card_name": null,
  "totem": null,
  "characteristics": [
    "Unique",
    "Living"
  ],
  "keywords": [
    "Tri-Chi"
  ],
  "abilities": [
    {
      "name": "Avoid Doom",
      "defensive_type": null,
      "text": "When this model flips the black joker, it may drain a (t) to discard it without effect and flip a new card."
    },
    {
      "name": "Happy Hour",
      "defensive_type": null,
      "text": "When this model activates, it may replace itself with Nia, Life of the Party and heal 2."
    },
    {
      "name": "Hard to Kill",
      "defensive_type": "unusual_defense",
      "text": "When this model suffers damage, if it has 2 or more health, it may not be reduced to below 1 health."
    }
  ],
  "actions": [
    {
      "name": "Wrist Blade",
      "action_type": "melee",
      "range": "(melee)1\"",
      "skill_value": 5,
      "skill_built_in_suit": "m",
      "skill_fate_modifier": null,
      "resist": "Df",
      "tn": null,
      "damage": "3",
      "is_signature": false,
      "soulstone_cost": 0,
      "costs_and_restrictions": "If the target is in base contact with this model this attack receives a (+).",
      "effects": null,
      "triggers": [
        {
          "name": "Divergent Path",
          "suit": "(fortitude)",
          "timing": "after_succeeding",
          "text": "Once per activation. This model may declare an action printed on its other title.",
          "is_mandatory": false,
          "soulstone_cost": 0
        },
        {
          "name": "Draw Out Secrets",
          "suit": "(t)(t)",
          "timing": "after_succeeding",
          "text": "Make a Scheme marker in base contact with the target.",
          "is_mandatory": false,
          "soulstone_cost": 0
        },
        {
          "name": "Pop In",
          "suit": "(m)",
          "timing": "after_succeeding",
          "text": "Place this model anywhere within 3\".",
          "is_mandatory": false,
          "soulstone_cost": 0
        },
        {
          "name": "Execute",
          "suit": "(c)",
          "timing": "after_succeeding",
          "text": "The target may either discard a card or drain a (fortitude). If it does neither, it is killed.",
          "is_mandatory": false,
          "soulstone_cost": 0
        }
      ],
      "category": "attack_actions"
    },
    {
      "name": "Dead Shot",
      "action_type": "missile",
      "range": "(gun)12\"",
      "skill_value": 6,
      "skill_built_in_suit": null,
      "skill_fate_modifier": null,
      "resist": "Df",
      "tn": null,
      "damage": null,
      "is_signature": false,
      "soulstone_cost": 0,
      "costs_and_restrictions": "This action may not target the same model more than once per activation.",
      "effects": "The target may either discard a card or drain a (fortitude). If it does neither, it is killed.",
      "triggers": [
        {
          "name": "Sloshed",
          "suit": "(c)",
          "timing": "after_succeeding",
          "text": "Target gains a Distracted token.",
          "is_mandatory": false,
          "soulstone_cost": 0
        }
      ],
      "category": "attack_actions"
    },
    {
      "name": "Adrenaline Rush",
      "range": null,
      "skill_value": null,
      "skill_built_in_suit": null,
      "skill_fate_modifier": null,
      "tn": null,
      "damage": null,
      "is_signature": true,
      "soulstone_cost": 0,
      "costs_and_restrictions": null,
      "effects": "This model declares a general action. If it has half of its maximum health or less, the generated action ignores engagement and \"once per\" restrictions.",
      "triggers": [],
      "category": "tactical_actions",
      "action_type": null
    }
  ],
  "source_pdf": "C:\\Users\\mbeck\\Documents\\GitHub\\Malifaux-4th-Edition-Tools\\source_pdfs\\Bayou\\Tri-Chi\\M4E_Stat_Tri-Chi_Nia_Fractured_Future.pdf",
  "merge_warnings": [],
  "extraction_notes": [
    "Fortitude icon rendered as (fortitude) in trigger suit for Divergent Path and in effect text for Execute and Dead Shot"
  ]
}